hdtimelines/__init__.py
hdtimelines/colorgen.py
hdtimelines/hdtimeline.py
hdtimelines/hdtimelineutils.py
hdtimelines/hdtopic.py
hdtimelines/lineorganiser.py
hdtimelines/pltimeline.py
hdtimelines/pltimelinehelpers.py
hdtimelines/pltutils.py
hdtimelines-0.1.1.dist-info/LICENSE
hdtimelines-0.1.1.dist-info/WHEEL
hdtimelines-0.1.1.dist-info/METADATA
hdtimelines-0.1.1.dist-info/RECORD
