Metadata-Version: 2.1
Name: hdtimelines
Version: 0.1.1
Summary: A Python package for creating graphical timelines of historical events
Author-email: David Harris <dharris3968@hotmail.co.uk>
Requires-Python: >=3.8
Classifier: License :: OSI Approved :: MIT License
Requires-Dist: pandas>=2.0.0
Requires-Dist: historicaldate>=0.1.2
Requires-Dist: plotly>=5.18.0
Project-URL: Documentation, https://hdtimelines.readthedocs.io/en/stable/
Project-URL: Home, https://github.com/dh3968mlq/hdtimelines
